pixel_font_builder/__init__.py
pixel_font_builder/bdf.py
pixel_font_builder/builder.py
pixel_font_builder/glyph.py
pixel_font_builder/meta.py
pixel_font_builder/metric.py
pixel_font_builder/opentype.py
pixel_font_builder/pcf.py
dotted_font_builder-0.0.1.dist-info/METADATA
dotted_font_builder-0.0.1.dist-info/WHEEL
dotted_font_builder-0.0.1.dist-info/licenses/LICENSE
dotted_font_builder-0.0.1.dist-info/RECORD
