Metadata-Version: 2.3
Name: dotted-font-builder
Version: 0.0.1
Summary: A library that helps create dotted style fonts.
Project-URL: homepage, https://github.com/OverflowCat/dotted-font-builder
Project-URL: source, https://github.com/OverflowCat/dotted-font-builder
Project-URL: issues, https://github.com/OverflowCat/dotted-font-builder/issues
Author: OverflowCat, TakWolf
Maintainer: OverflowCat
License: MIT License
Keywords: font,pixel
Classifier: License :: OSI Approved :: MIT License
Classifier: Operating System :: OS Independent
Classifier: Programming Language :: Python :: 3
Requires-Python: >=3.11
Requires-Dist: bdffont>=0.0.26
Requires-Dist: fonttools[woff]>=4.55.0
Requires-Dist: pcffont>=0.0.15
Requires-Dist: pypng>=0.20220715.0
Requires-Dist: pytest>=8.3.3
